{
    "URL post": "https://touch.facebook.com/1792761284389317",
    "Has media": true,
    "Media": [
        "https://lm.facebook.com/l.php?u=https%3A%2F%2Fvnexpress.net%2Fdoi-quan-cay-view-tren-internet-trung-quoc-4437949.html&h=AT1TFNbyKVc2SohGuQmezpnlB6FQ0IIWon7OUQDwCodCibDYS1M9rTyoZn-dY2uohDyOgiGZ1rmMBHtL02AUJA9J2ekzHYAxl7DEll7VTkes6SOG-5posg9djbxYjtpOy_TSCuV9K8-CDDnsFmwYwAJCLKlf8D_HAyYJ0399icgqBzHvBz2ZQkCrsJ6jT4G2Hw"
    ],
    "Content": "Andrey Shevchenko đã chia sẻ một liên kết với nhóm: J2TEAM Community.\nHôm qua lúc 15:37 ·\nhttps://vnexpress.net/doi-quan-cay-view-tren-internet-trung-quoc-4437949.html\nĐằng sau những lượt xem, theo dõi khổng lồ trên mạng xã hội Trung Quốc không còn là những chiếc smartphone mà được nâng cấp thành các dàn bo mạch chủ.\n#j2team_share\nVNEXPRESS.NET\nĐội quân 'cày view' trên Internet Trung Quốc\nĐằng sau những lượt xem, theo dõi khổng lồ trên mạng xã hội Trung Quốc không còn là những chiếc smartphone mà được nâng cấp thành các dàn bo mạch chủ.",
    "Comment": [
        {
            "Owner": "Lành Minh Huấn",
            "Cmt": "Vn thấy có nhiều r, pháp sư vn cũng học theo nhah lắm",
            "Number reply": 0
        },
        {
            "Owner": "Dang Thai",
            "Cmt": "vừa hôm qua đi root dạo gặp một dàn la lá như này",
            "Number reply": 0
        },
        {
            "Owner": "Bồ Công Anh",
            "Cmt": "Farm có 2 dạng. Nhưng phonefarm xịn xò hơn chứ sao lại upgrade",
            "Number reply": 9,
            "Reply cmt": [
                {
                    "Owner": "Nguyễn Trung Nhân",
                    "Cmt": "Bồ Công Anh có thể hiệu năng không bằng chăng, chắc tìm được quả giả lập xịn nên đổi qua",
                    "Number reply": 0
                },
                {
                    "Owner": "Bồ Công Anh",
                    "Cmt": "Nguyễn Trung Nhân Hiệu năng fone thấp hơn nhưng trust hơn nhiều",
                    "Number reply": 0
                },
                {
                    "Owner": "Nguyễn Trung Nhân",
                    "Cmt": "Bồ Công Anh chắc khả năng bên đó làm được giả lập ngon mới chuyển chứ giàn farm này mà bị detect thì cũng thốn lắm",
                    "Number reply": 0
                },
                {
                    "Owner": "Bồ Công Anh",
                    "Cmt": "Nguyễn Trung Nhân ah, ae mình đọc ko đọc bài :v. \"bo mạch chủ của điện thoại di động\", kiểu chạy ko có màn hình chứ k phải là giả lập",
                    "Number reply": 0
                },
                {
                    "Owner": "Nguyễn Trung Nhân",
                    "Cmt": "Bồ Công Anh quả title của chủ thớt thế thì chịu =)))",
                    "Number reply": 0
                },
                {
                    "Owner": "Mai Viên",
                    "Cmt": "Bồ Công Anh thay vì dùng các dòng điện thoại có sẵn, upgrade bằng cách tạo ra những chiếc máy chuyên dùng để phonefarm. bỏ pin và bỏ màn hình để giảm thiểu chi phí , tiết kiệm điện , lắp thêm tản nhiệt tránh nóng máy giúp tăng hiệu năng cao hơn",
                    "Number reply": 0
                },
                {
                    "Owner": "Bồ Công Anh",
                    "Cmt": "Mai Viên do ae hiểu nhầm thành up lên dùng pc vs workstation :)))",
                    "Number reply": 0
                },
                {
                    "Owner": "Andrey Shevchenko",
                    "Cmt": "Nguyễn Trung Nhân Title/ highlight bên báo chứ mình có làm gì đâu 🙄",
                    "Number reply": 0
                },
                {
                    "Owner": "Đỗ Tuấn Anh",
                    "Cmt": "Mai Viên Nhìn trong hình thì nó vẫn là dùng main sẵn của smartphone thôi, kiểu mua số lượng lớn các máy hỏng màn, cấu hình quá cũ...\nKinh tế và trust hơn nhiều so với đặt làm pcb riêng.",
                    "Number reply": 0
                }
            ]
        },
        {
            "Owner": "Công Nguyễn",
            "Cmt": "Ké, Các bác nào trong nghề cho em hỏi thông tin về bộ giả lập pin trong phonefarm với. em làm sạc điện thoại thuê mà làm hỏng pin của người ta suốt.",
            "Number reply": 12,
            "Reply cmt": [
                {
                    "Owner": "Hai Nam",
                    "Cmt": "Công Nguyễn Ở Vn có bộ như hình trên rồi nha bạn",
                    "Number reply": 0
                },
                {
                    "Owner": "Công Nguyễn",
                    "Cmt": "Hai Nam Cái đó mình biết mà, ý mình muốn hỏi thông tin modul giả lập pin này ấy bác.",
                    "Number reply": 0
                },
                {
                    "Owner": "Hai Nam",
                    "Cmt": "Công Nguyễn m ko hiểu ý b , nhưng như hình là điện thoại thật 100% ko dùng pin",
                    "Number reply": 0
                },
                {
                    "Owner": "Công Nguyễn",
                    "Cmt": "Hai Nam Thế bác k hiểu về box này rồi, điện thoại phải cắm pin thì nó mới lên nguồn để dùng, nhưng nếu dùng pin thì sẽ tốn kém vì để điều khiển thì họ dùng kết nối qua ADB phải cắm cáp 24/24, lâu ngày pin sẽ bị chai nên họ sẽ dùng 1 cái modul để cắm vào giả làm pin nên sẽ k sợ nổ pin hay chai pin gì cả. cái mình muốn hỏi là thông tin của cái modul đó!",
                    "Number reply": 0
                },
                {
                    "Owner": "Thái Hồng Hải",
                    "Cmt": "Thế thì là dummy battery thôi",
                    "Number reply": 0
                },
                {
                    "Owner": "Công Nguyễn",
                    "Cmt": "Thái Hồng Hải thank bác để e tìm kiếm xem sao.",
                    "Number reply": 0
                },
                {
                    "Owner": "Nguyễn Xoáy",
                    "Cmt": "Công Nguyễn k biết sao chứ bt cấp nguồn thì như thợ sửa cấp cho đt thui 3.7v cấp theo jack pin là ok mà, cái đen đen hình như k phải pin",
                    "Number reply": 0
                },
                {
                    "Owner": "Đinh Đại Dương",
                    "Cmt": "Công Nguyễn bác ơi bác check ib em được không ạ.",
                    "Number reply": 0
                },
                {
                    "Owner": "Công Nguyễn",
                    "Cmt": "Ib đi bác",
                    "Number reply": 0
                },
                {
                    "Owner": "Job Steve",
                    "Cmt": "Công Nguyễn sạc điện thoại mà cũng thuê ah ta?",
                    "Number reply": 0
                },
                {
                    "Owner": "Đỗ Tuấn Anh",
                    "Cmt": "Công Nguyễn Ngày trước mình cày game làm con tablet bị phồng pin, sau mình tháo pin chơi luôn cái dây cáp cấp nguồn mà thợ sửa điện thoại hay dùng này, cắm 24/24 :v",
                    "Number reply": 0
                },
                {
                    "Owner": "Đỗ Tuấn Anh",
                    "Cmt": "Còn kiểu nữa là tháo cái bo mạch trên cục pin, hàn luôn dây cấp nguồn vào đó. Cái này kinh tế hơn mua cáp chuyên dùng, tiết kiệm 100k :v",
                    "Number reply": 0
                }
            ]
        },
        {
            "Owner": "Nguyễn Phụng",
            "Cmt": "Đồ thật nó made in china được ko lẽ mấy cái view ảo này làm khó được sao",
            "Number reply": 0
        },
        {
            "Owner": "Tay Trắng",
            "Cmt": "Vn cũng đâu kém bác. Kkk fake nhiệt tình",
            "Number reply": 0
        },
        {
            "Owner": "Lê Phúc",
            "Cmt": "😃 cái này vn cũng có lâu rồi chứ xa xôi gì",
            "Number reply": 0
        },
        {
            "Owner": "Vu Nguyen",
            "Cmt": "đầu tư 1 dàn bé bé mini như này thì mất chi phí nhiều không anh em nhỉ",
            "Number reply": 10,
            "Reply cmt": [
                {
                    "Owner": "Phan Đình Đức",
                    "Cmt": "Vu Nguyen còn chưa biết trong đó có gì thì ko định giá đc đâu bác",
                    "Number reply": 0
                },
                {
                    "Owner": "Vu Nguyen",
                    "Cmt": "Phan Đình Đức vâng e cũng dazng9 tìm hiểu bộ môn này",
                    "Number reply": 0
                },
                {
                    "Owner": "Alex Cao",
                    "Cmt": "Phan Đình Đức nhìn thì có vẻ là chỉ lấy bo mạch điện thoại. Quan trọng là phần mềm quản lý nữa",
                    "Number reply": 0
                },
                {
                    "Owner": "Nguyễn Thái Dương",
                    "Cmt": "Vu Nguyen 100 con phone ~ 120tr\nkệ để 100 con phone ~ 3tr5\nphần mềm tuyd crack hay trả phis~x tr\ntài khoản clone (fb, ins, tiktok) xxx tr\ntiền điện mỗi tháng ~ 3tr/1 tháng",
                    "Number reply": 0
                },
                {
                    "Owner": "Vu Nguyen",
                    "Cmt": "Nguyễn Thái Dương thank bạn , tại mình cũng đang dự định làm 1 dàn tầm 10 con để nuôi",
                    "Number reply": 0
                },
                {
                    "Owner": "Nguyễn Thái Dương",
                    "Cmt": "Vu Nguyen 10 con thì k ăn thua đâu ạ, vì sẽ k thể hồi vốn đc trong vòng 1 năm. hiện tại mảng seeding fb giá đang vô cùng rẻ vì có nhiều tools buff bằng pages nên phương pháp như trên chỉ chạy views và các nền tảng khác là ổn thôi đừng đâm vào fb nhé",
                    "Number reply": 0
                },
                {
                    "Owner": "Vu Nguyen",
                    "Cmt": "Nguyễn Thái Dương dạ k mình chủ yếu tạo để cày view cho ytb kênh mình làm thương hiệu là chính chứ k bkt",
                    "Number reply": 0
                },
                {
                    "Owner": "Nguyễn Thái Dương",
                    "Cmt": "Vu Nguyen thế thì bác tham khảo phonefarm, thu mua những con máy hỏng màn về cho rẻ",
                    "Number reply": 0
                },
                {
                    "Owner": "Vu Nguyen",
                    "Cmt": "Nguyễn Thái Dương vâng",
                    "Number reply": 0
                },
                {
                    "Owner": "Vu Nguyen",
                    "Cmt": "Nguyễn Thái Dương mà cái này mình nghĩ pm quản trị , thay đổi proxy các thứ mới cốt lõi",
                    "Number reply": 0
                }
            ]
        },
        {
            "Owner": "Trần Đức Anh",
            "Cmt": "E thắc măc tại sao k dùng pc để giả lập\nClone nhiu tài khoản ra mà phải dùng nhìu đt như v ạ",
            "Number reply": 1,
            "Reply cmt": [
                {
                    "Owner": "Trần Nam",
                    "Cmt": "Trần Đức Anh pc đắt gấp mấy lần",
                    "Number reply": 0
                }
            ]
        },
        {
            "Owner": "Nguyễn Trọng Khang",
            "Cmt": "Lê Bạch Hiệp",
            "Number reply": 0
        },
        {
            "Owner": "Trương Đức Cường",
            "Cmt": "Phần mềm quản lý lũ này mới là cốt lõi :(",
            "Number reply": 2,
            "Reply cmt": [
                {
                    "Owner": "Hanh",
                    "Cmt": "Trương Đức Cường có mà",
                    "Number reply": 0
                },
                {
                    "Owner": "Trương Đức Cường",
                    "Cmt": "Thì chắc chắn là phải có còn phần cứng quan trọng gì đâu :v.",
                    "Number reply": 0
                }
            ]
        },
        {
            "Owner": "Quyet Nguyenquang",
            "Cmt": "đầu tư bộ này về làm vẫn ra tiền",
            "Number reply": 0
        },
        {
            "Owner": "Ngô Đức Thành",
            "Cmt": "Đầu tư bộ này đắt không nhỉ",
            "Number reply": 0
        },
        {
            "Owner": "Đỗ Tuấn Anh",
            "Cmt": "Ủa nó vẫn là bo mạch của smartphone mà, tháo hết những thứ không cần thiết như pin, màn hình, loa... thôi",
            "Number reply": 0
        },
        {
            "Owner": "Dương Chấy",
            "Cmt": "Andriy Shevchenko mới là tên đúng bác ơi",
            "Number reply": 2,
            "Reply cmt": [
                {
                    "Owner": "Andrey Shevchenko",
                    "Cmt": "Dương Chấy e hàng fake thôi mà bác :D",
                    "Number reply": 0
                },
                {
                    "Owner": "Thang Holmes",
                    "Cmt": "Dương Chấy bác fan sheva à",
                    "Number reply": 0
                }
            ]
        },
        {
            "Owner": "Trần Quang Huy",
            "Cmt": "Huynh Nhu Tran",
            "Number reply": 0
        },
        {
            "Owner": "Lê Danh Công",
            "Cmt": "Sao k dùng vps mà treo nhỉ",
            "Number reply": 0
        }
    ]
}