{"URL post": "https://touch.facebook.com/1783080952024017", "Content": "Mức lương cao nhất của một người mà bạn từng thấy là bao nhiêu?\n#j2team_discussion // video: Bino chém tiếng Anh", "Comment": [{"Owner": "Trường Lâm", "URL Owner": "https://m.facebook.com/caphethichchupanh?groupid=364997627165697&refid=18&__tn__=R", "Cmt": "lương cao thì không rõ chứ thấy bác Duy Luân bên tinhte (kênh yt riêng nữa) làm data engineer mà con macbook pro m1 max 16inch 32GB ram gần trăm củ mà bác ý mua để làm việc dễ dàng như không ý, đồ công nghệ khác cũng thế, đắt rẻ gì cũng quất liền tay, thậm chí mua về give away nữa.", "Number reply": 19, "Reply cmt": [{"Owner": "Minh Huy", "URL Owner": "https://m.facebook.com/huydminh?groupid=364997627165697&__tn__=R", "Cmt": "Trường Lâm data engineer có range hơn dev khoảng 20% , team lead khoảng 1k biden thì ổng cũng đâu đó khoảng 1k2 - 1k5, ở Tp HCM không gọi là cao đâu; còn mấy món đồ công nghệ trên kênh đó đừng vội tin là chính chủ nhé 😌", "Number reply": 0}, {"Owner": "Phạm Tâm", "URL Owner": "https://m.facebook.com/tolpham0?groupid=364997627165697&__tn__=R", "Cmt": "Minh Huy team lead 1k thấp vậy @@", "Number reply": 0}, {"Owner": "Trường Lâm", "URL Owner": "https://m.facebook.com/caphethichchupanh?groupid=364997627165697&__tn__=R", "Cmt": "Minh Huy má như bác nói thật thì buồn quá :))))))))))))", "Number reply": 0}, {"Owner": "Minh Huy", "URL Owner": "https://m.facebook.com/huydminh?groupid=364997627165697&__tn__=R", "Cmt": "Phạm Tâm mình lấy avera chứ ko lấy top, có thể team lead 2k thì cũng sẽ có team lead chỉ khoảng 18-20tr", "Number reply": 0}, {"Owner": "Tài Tuệ Nguyễn", "URL Owner": "https://m.facebook.com/taitue.nguyen?groupid=364997627165697&__tn__=R", "Cmt": "Minh Huy lead mà 1k nghe hơi ít nhỉ", "Number reply": 0}, {"Owner": "Tài Tuệ Nguyễn", "URL Owner": "https://m.facebook.com/taitue.nguyen?groupid=364997627165697&__tn__=R", "Cmt": "Trường Lâm mạnh dạn đoán lương bác ý ít nhất 2k net 😛", "Number reply": 0}, {"Owner": "Nguyen Tri Dan", "URL Owner": "https://m.facebook.com/nguyentridan?groupid=364997627165697&__tn__=R", "Cmt": "Minh Huy ông trên trời rơi xuống à mà team lead data engineer 1k-1k2?", "Number reply": 0}, {"Owner": "Minh Huy", "URL Owner": "https://m.facebook.com/huydminh?groupid=364997627165697&__tn__=R", "Cmt": "Nguyen Tri Dan ông trên trời rơi xuống hay sao mà k thấy cmt của tui ghi rõ ràng \"1k2-1k5\" ???", "Number reply": 0}, {"Owner": "Nguyen Tri Dan", "URL Owner": "https://m.facebook.com/nguyentridan?groupid=364997627165697&__tn__=R", "Cmt": "Minh Huy ông trên trời rơi xuống hay sao mà team lead data 1k2 - 1k5? Hay ông đang làm cty bóc lột mà không biết :)))", "Number reply": 0}, {"Owner": "Minh Huy", "URL Owner": "https://m.facebook.com/huydminh?groupid=364997627165697&__tn__=R", "Cmt": "Nguyen Tri Dan tay nhanh hơn não, lắm mồm", "Number reply": 0}, {"Owner": "Nguyen Tri Dan", "URL Owner": "https://m.facebook.com/nguyentridan?groupid=364997627165697&__tn__=R", "Cmt": "Minh Huy đọc kỹ lại đi thanh niên, m nói phía trên team lead có 1k kìa :)) ếch ngồi đáy giếng", "Number reply": 0}, {"Owner": "Nguyễn Anh Quân", "URL Owner": "https://m.facebook.com/nguyenanhquanbg?groupid=364997627165697&__tn__=R", "Cmt": "không chính chủ là sao bác", "Number reply": 0}, {"Owner": "Trường Lâm", "URL Owner": "https://m.facebook.com/caphethichchupanh?groupid=364997627165697&__tn__=R", "Cmt": "Tài Tuệ Nguyễn em thấy lương cơ bản ở bên US đã là $5000 rồi, kinh khủng thật. Về Việt Nam cơ sở dữ liệu ít hơn thì làm cho các công ty to mạnh doạn đoán hơn bác 1 tý, tầm 2,6-2,7k :))))", "Number reply": 0}, {"Owner": "Quach Tuan Anh", "URL Owner": "https://m.facebook.com/tuananh.qaa?groupid=364997627165697&__tn__=R", "Cmt": "thì ổng cũng đâu đó khoảng 1k2 - 1k5 => data engineer senior đã ko có mức này rồi , lead bèo cũng phải 2k5 chứ làm gì 1k5 =))", "Number reply": 0}, {"Owner": "Minh Huy", "URL Owner": "https://m.facebook.com/huydminh?groupid=364997627165697&__tn__=R", "Cmt": "Nguyễn Anh Quân 1 số món đc mượn để quay video, đa số còn lại chính chủ", "Number reply": 0}, {"Owner": "Minh Huy", "URL Owner": "https://m.facebook.com/huydminh?groupid=364997627165697&__tn__=R", "Cmt": "Quach Tuan Anh team lead khác senior, senior có thể làm team lead chứ team lead chưa chắc đã là senior; range mà các ông trên nói là role team lead kiêm nhiệm cả effort của senior, tất nhiên lương phải cao rồi;\n\ncòn role team lead thuần (chỉ có quản lý tiến độ, breakdown task, review code và training new member) thì range 1k đến 1k2 là hợp lý; mà data engineer hơn dev ít nhất 20% thì 1k5 chứ gì nữa ? Hơn nữa mình cũng chỉ phỏng đoán, còn lương thực tế bác Duy Luân lãnh là bao nhiêu chắc chỉ có vợ biết 🥲", "Number reply": 0}, {"Owner": "Ngô Toàn", "URL Owner": "https://m.facebook.com/Toannhse?groupid=364997627165697&__tn__=R", "Cmt": "Minh Huy Tầm Duy Luan phải hơn, tầm lèo bèo như mình đã tầm đấy rồi, range của lead nó vô vàn lắm.", "Number reply": 0}, {"Owner": "Minh Huy", "URL Owner": "https://m.facebook.com/huydminh?groupid=364997627165697&__tn__=R", "Cmt": "Ngô Toàn cũng khó nói lắm bác, giá thị trường cao thì chỉ đúng ở mấy cty top, còn những nơi khác phụ thuộc vào range của cty, và cả budget của các project...\n\nTuy nhiên việc mua nhà ở Tp HCM cũng thốn phết, bác Duy Luân chắc cũng phải có thu nhập khoảng 2k thì mới đc như vậy", "Number reply": 0}, {"Owner": "Tuấn Nguyễn", "URL Owner": "https://m.facebook.com/tuandeveloper02?groupid=364997627165697&__tn__=R", "Cmt": "Trường Lâm Lương ông ý cũng hơn 30 tí thôi. Căn bản là chi tiêu hợp lý là cuộc sống thoải mái thôi bác. Thay vì trả một đống thì nên trả góp mặc dù dư tiền.", "Number reply": 0}]}, {"Owner": "Cường Lê", "URL Owner": "https://m.facebook.com/cao.le.108?groupid=364997627165697&refid=18&__tn__=R", "Cmt": "Lần cao nhất là tôi nghe nhân viên của 1 cửa hàng bán ốp điện thoại lớn trên đường 3/2 quận 10 sài gòn: bà chủ cửa hàng 1 ngày bán được tầm 60 - 70 triệu, lãi tầm 30- 40 triệu 1 ngày", "Number reply": 10, "Reply cmt": [{"Owner": "Linh Chi", "URL Owner": "https://m.facebook.com/profile.php?id=100015599467940&groupid=364997627165697&__tn__=R", "Cmt": "Cường Lê đấy ko phải lương 😅 profit # salary", "Number reply": 0}, {"Owner": "Minh Chiến", "URL Owner": "https://m.facebook.com/mchien477?groupid=364997627165697&__tn__=R", "Cmt": "Cường Lê bà chủ chắc là ốp PA rồi, mình là khách guột ở đấy :))", "Number reply": 0}, {"Owner": "Borjigin Nergui II", "URL Owner": "https://m.facebook.com/borjigin.nerguiii.9?groupid=364997627165697&__tn__=R", "Cmt": "Cường Lê Xin địa chỉ", "Number reply": 0}, {"Owner": "Cường Lê", "URL Owner": "https://m.facebook.com/cao.le.108?groupid=364997627165697&__tn__=R", "Cmt": "Minh Chiến đúng rồi đó bác", "Number reply": 0}, {"Owner": "Cường Lê", "URL Owner": "https://m.facebook.com/cao.le.108?groupid=364997627165697&__tn__=R", "Cmt": "Borjigin Nergui II Phụ Kiện Điện Thoại Phương Anh\n093 870 11 11\nhttps://maps.app.goo.gl/ksAFm7nKSRaBFyrj6", "Number reply": 0}, {"Owner": "Nguyen Thi Hanh", "URL Owner": "https://m.facebook.com/nguyenthihanh899?groupid=364997627165697&__tn__=R", "Cmt": "Cường Lê tiệm Phương Anh gì đấy í, mở thêm gian nhà bên cạnh nữa. Chỗ đấy là chỗ bán đông khách nhất của cả dãy đường 3/2 ấy. Ngày vài chục triệu cũng không khó hiểu lắm", "Number reply": 0}, {"Owner": "Cường Lê", "URL Owner": "https://m.facebook.com/cao.le.108?groupid=364997627165697&__tn__=R", "Cmt": "Nguyen Thi Hanh tất cả đều là mặt bằng nhà mua lại hết luôn á chị. Chưa hết, dọc con đường đó còn vài tiệm nữa nhưng là cho anh em thuê lại mở bán.", "Number reply": 0}, {"Owner": "Nguyen Thi Hanh", "URL Owner": "https://m.facebook.com/nguyenthihanh899?groupid=364997627165697&__tn__=R", "Cmt": "Cường Lê Mình k rõ mặt bằng của nhà hay thuê nhưng mà cái khúc đường 3/2 đó là cả khu bán phụ kiện đt mà có mỗi tiệm đó là khách đông nhất. Mình cũng khách ruột ở đó mà 😄", "Number reply": 0}, {"Owner": "Đỗ Tất Thắng", "URL Owner": "https://m.facebook.com/dothang1310?groupid=364997627165697&__tn__=R", "Cmt": "Cường Lê lương khác doanh thu bạn ơi. Để nói về thu nhập thì vô kể lắm...", "Number reply": 0}, {"Owner": "Nguyễn Minh", "URL Owner": "https://m.facebook.com/minfabulous?groupid=364997627165697&__tn__=R", "Cmt": "Nguyen Thi Hanh chỗ có cái bà ngồi ghế cao chót vót xong đeo micro vô gọi nhân viên lấy đồ đúng ko. chỗ đó đúng bự luôn, mua ở đó mấy lần nói chung bán mấy cái đồ ốp lưng + dán cường lực thì khỏe re, ko sợ bảo hành mấy. mà giá rẻ bù lại biên độ lợi nhuận cao", "Number reply": 0}]}, {"Owner": "Lê Chí Tâm", "URL Owner": "https://m.facebook.com/citizen76d?groupid=364997627165697&refid=18&__tn__=R", "Cmt": "Tận mắt thấy bảng lương 600tr của sếp mình, từng tháng\nMà đó là 1 năm trước rồi lúc còn là trưởng phòng KD, giờ lên thêm 2 cấp nữa rồi", "Number reply": 3, "Reply cmt": [{"Owner": "Thien Le", "URL Owner": "https://m.facebook.com/profile.php?id=100004263875299&groupid=364997627165697&__tn__=R", "Cmt": "Lê Chí Tâm tui thì sợ mấy ô bảng lương thấp hơn. Đã chứng kiến sếp có mức lương thấp hơn tui. Nhưng giá trị tài sản được cty thưởng hay cp hàng năm thì ối giời ơi.", "Number reply": 0}, {"Owner": "Thien Le", "URL Owner": "https://m.facebook.com/profile.php?id=100004263875299&groupid=364997627165697&__tn__=R", "Cmt": "Lê Chí Tâm và thế chấp thì được ưu tiên hơn tín chấp khi tạo thẻ tín dụng và vay ngân hàng.", "Number reply": 0}, {"Owner": "Nhã Nguyễn Thanh", "URL Owner": "https://m.facebook.com/nha.thanh.824?groupid=364997627165697&__tn__=R", "Cmt": "Thien Le đúng r bác :v có quả sếp lương 3 triệu nữa kia =)) còn lại quy qua thường và cp công ty =)) nên ổng lúc nào cũng than lương 3 triệu :v", "Number reply": 0}]}, {"Owner": "Tran Duy Thanh", "URL Owner": "https://m.facebook.com/thanh.deeptryyy?groupid=364997627165697&refid=18&__tn__=R", "Cmt": "Anh này làm vid hay với chất lượng vl. Nhưng cảm giác cứ bị underate thế nào ấy :v", "Number reply": 7, "Reply cmt": [{"Owner": "Bùi Quốc Khôi", "URL Owner": "https://m.facebook.com/khoi.buiquoc?groupid=364997627165697&__tn__=R", "Cmt": "Tran Duy Thanh k biết sao chứ ông ý nc em cứ thấy chậm chậm nên lướt luôn =))", "Number reply": 0}, {"Owner": "Tran Duy Thanh", "URL Owner": "https://m.facebook.com/thanh.deeptryyy?groupid=364997627165697&__tn__=R", "Cmt": "Bùi Quốc Khôi bác xem kĩ mấy nội dung của anh này mới với bổ ích lắm :)). Còn chậm phải nói tới content của cha nội giáo viên dạy TA đẹp trai gì gì chuyên chỉ mấy câu thành ngữ/ từ lóng \"uầy từ này khó vãi\" trong TA ấy. Nói vớ vẩn mãi mới đi vào nội dung =)))", "Number reply": 0}, {"Owner": "Bùi Quốc Khôi", "URL Owner": "https://m.facebook.com/khoi.buiquoc?groupid=364997627165697&__tn__=R", "Cmt": "Tran Duy Thanh thì có ích với lại biết được nhiều mà, vd hôm nào cực kỳ rảnh sẽ chịu khó dừng lại xem cũng hay, chứ thường thì sẽ lướt luôn =)))) ổng nói thì bth mà mình cứ cảm thấy chậm chậm thế nào", "Number reply": 0}, {"Owner": "Nga Tuyết Nguyễn", "URL Owner": "https://m.facebook.com/nguyen.t.nga.18?groupid=364997627165697&__tn__=R", "Cmt": "Tran Duy Thanh mình có follow anh này, thấy anh này nội dung hay, dễ hiểu, vui vẻ, nói chuyện thẳng thắn. Nhưng không thấy anh này bị underrate.", "Number reply": 0}, {"Owner": "Tran Thanh Binh", "URL Owner": "https://m.facebook.com/profile.php?id=100024240312670&groupid=364997627165697&__tn__=R", "Cmt": "Tran Duy Thanh bác nói dũng ai eo ad :))))", "Number reply": 0}, {"Owner": "Trường Lâm", "URL Owner": "https://m.facebook.com/caphethichchupanh?groupid=364997627165697&__tn__=R", "Cmt": "Tran Duy Thanh trừ vế bị underated ra thì em đồng ý vs bác, vid hay hay hài hài nói chuyện dễ nghe nữa mà toàn nói mấy cái hay", "Number reply": 0}, {"Owner": "Trầnn Quang Hùng", "URL Owner": "https://m.facebook.com/hung.tranquang.258?groupid=364997627165697&__tn__=R", "Cmt": "Tran Duy Thanh không được viral khác với bị underrate", "Number reply": 0}]}, {"Owner": "Huy Không", "URL Owner": "https://m.facebook.com/huykhoong?groupid=364997627165697&refid=18&__tn__=R", "Cmt": "Bạn mình Lê Bá Trình full time trader + fund trader + cố vấn cao cấp cho quỹ đầu tư tháng $100k. Ngoài chiếc glc 300 đi loanh quanh ra thì chẳng ai biết là người giàu, vẫn chỉ ip xsm, quần cộc áo thun và một chiếc mi band 4.", "Number reply": 3, "Reply cmt": [{"Owner": "Loạn Loạn Luôn", "URL Owner": "https://m.facebook.com/luandt222?groupid=364997627165697&__tn__=R", "Cmt": "Huy Không thật à bác?", "Number reply": 0}, {"Owner": "Huy Không", "URL Owner": "https://m.facebook.com/huykhoong?groupid=364997627165697&__tn__=R", "Cmt": "Loạn Loạn Luôn I'm for real", "Number reply": 0}, {"Owner": "Loạn Loạn Luôn", "URL Owner": "https://m.facebook.com/luandt222?groupid=364997627165697&__tn__=R", "Cmt": "Huy Không hic, vậy em phải xin tư vấn mới đc, em cũng đang muốn làm cho quỹ đầu tư, nhưng không biết phải làm như nào", "Number reply": 0}]}, {"Owner": "Thành Cang", "URL Owner": "https://m.facebook.com/ngothanhcang96?groupid=364997627165697&refid=18&__tn__=R", "Cmt": "230tr 1 tháng sáng đi chiều về , t7 cn nghỉ , thích làm làm , chán xin off , trưởng khoa sét nghiệm của 1 bệnh viện bên mẽo . đời hok lo âu gì . sáng 8h vô chiều 4-5h về tối nhậu , chả doanh số chả thi đua chả ngán ai to mồm chửi bới , sáng ngủ dậy tự nhiên ho cái xin off luôn , hok cần xin trước ,", "Number reply": 0}, {"Owner": "Tiny Thanh Nhã", "URL Owner": "https://m.facebook.com/ieu.anh.nha.1?groupid=364997627165697&refid=18&__tn__=R", "Cmt": "Mình làm DLV lương tháng 3 củ còn không thèm lấy của nhà nước nè.\n<(\")", "Number reply": 1, "Reply cmt": [{"Owner": "Lưu Ngọc Tú", "URL Owner": "https://m.facebook.com/luu.ngoctu.1?groupid=364997627165697&__tn__=R", "Cmt": "Tiny Thanh Nhã công nhận ứ thèm", "Number reply": 0}]}, {"Owner": "Đỗ Hải Phong", "URL Owner": "https://m.facebook.com/dohaiphong.dsk?groupid=364997627165697&refid=18&__tn__=R", "Cmt": "Mình làm lương 20k/giờ đây", "Number reply": 1, "Reply cmt": [{"Owner": "Toàn Khánh", "URL Owner": "https://m.facebook.com/profile.php?id=100045298147743&groupid=364997627165697&__tn__=R", "Cmt": "Đỗ Hải Phong Circle K xin chào!", "Number reply": 0}]}, {"Owner": "Thạch Phương", "URL Owner": "https://m.facebook.com/faraway109?groupid=364997627165697&refid=18&__tn__=R", "Cmt": "Giám đốc điều hành 1 nhà máy gia công cho Adidas và NB\nĐâu đó 100k/ tháng\nChưa tính cuối năm ăn chia lợi nhuận", "Number reply": 0}, {"Owner": "Ngọc Vũ", "URL Owner": "https://m.facebook.com/ngocvupro97?groupid=364997627165697&refid=18&__tn__=R", "Cmt": "E làm thợ xăm, thì biết mấy master trong nghề làm khoảng 60tr/ tiếng 🥲", "Number reply": 3, "Reply cmt": [{"Owner": "Trang Thu", "URL Owner": "https://m.facebook.com/profile.php?id=100034816873332&groupid=364997627165697&__tn__=R", "Cmt": "Ngọc Vũ 60 triệu ôi 1 giờ bằng thu nhập bình quân 1 người Việt Nam chacs mấy người đó thuộc top rồi", "Number reply": 0}, {"Owner": "Ngọc Vũ", "URL Owner": "https://m.facebook.com/ngocvupro97?groupid=364997627165697&__tn__=R", "Cmt": "Trang Thu còn mức độ trung bình thì tầm 2-10tr/ tiếng", "Number reply": 0}, {"Owner": "Trang Thu", "URL Owner": "https://m.facebook.com/profile.php?id=100034816873332&groupid=364997627165697&__tn__=R", "Cmt": "Ngọc Vũ k ngờ nghề đó thu nhập cao thế luôn", "Number reply": 0}]}, {"Owner": "Thành An", "URL Owner": "https://m.facebook.com/nix4lg1?groupid=364997627165697&refid=18&__tn__=R", "Cmt": "Mn cho mình hỏi cái wifi 6 kia là gì vậy ạ tự nhiên e thấy tên PC của mình trong đó", "Number reply": 0}, {"Owner": "Nguyễn Nam", "URL Owner": "https://m.facebook.com/profile.php?id=100035837837394&groupid=364997627165697&refid=18&__tn__=R", "Cmt": "tôi cũng có ông anh sn 96 học bách khoa lương 3k biden :))", "Number reply": 0}, {"Owner": "Kien Pham", "URL Owner": "https://m.facebook.com/trungkien?groupid=364997627165697&refid=18&__tn__=R", "Cmt": "Ông ng quen mình làm app, mỗi tháng cỡ $27k. Giờ chắc phải hơn $30k. Đó mới là 1 app 🥺", "Number reply": 3, "Reply cmt": [{"Owner": "Lê Duy Tùng", "URL Owner": "https://m.facebook.com/tungldqn?groupid=364997627165697&__tn__=R", "Cmt": "Kien Pham a có thể chia sẻ là làm app j ko ak", "Number reply": 0}, {"Owner": "Nguyễn Minh Khoa", "URL Owner": "https://m.facebook.com/na61er?groupid=364997627165697&__tn__=R", "Cmt": "Lê Duy Tùng mô bai dì vé lộp bơ chứ gì nữa = ))", "Number reply": 0}, {"Owner": "Kien Pham", "URL Owner": "https://m.facebook.com/trungkien?groupid=364997627165697&__tn__=R", "Cmt": "Lê Duy Tùng mình cũng kg biết, họ dấu bí mật", "Number reply": 0}]}, {"Owner": "Uyển An", "URL Owner": "https://m.facebook.com/meowwww12?groupid=364997627165697&refid=18&__tn__=R", "Cmt": "Người có lương cao nhất mình từng tiếp xúc là 60-70tr, cái này là vừa ra trường, ảnh rất ghét ai khen ảnh giỏi, mình chỉ khen anh giỏi quá là mình bị doạ block :)", "Number reply": 3, "Reply cmt": [{"Owner": "Manh Viet", "URL Owner": "https://m.facebook.com/viet.trinhmanh.hp?groupid=364997627165697&__tn__=R", "Cmt": "Uyển An thế chủ động unfriend thôi 😂", "Number reply": 0}, {"Owner": "Phúc Ngô", "URL Owner": "https://m.facebook.com/duy.phuc.7524?groupid=364997627165697&__tn__=R", "Cmt": "Uyển An tán đc ổng chưa b", "Number reply": 0}, {"Owner": "Uyển An", "URL Owner": "https://m.facebook.com/meowwww12?groupid=364997627165697&__tn__=R", "Cmt": "Phúc Ngô mình tán anh í từ hồi anh í còn ăn mì gói thay cơm í :v (ko phải do nghèo, mà do tiết kiệm 1 cách kinh dị)", "Number reply": 0}]}, {"Owner": "Tân Lê", "URL Owner": "https://m.facebook.com/tanpear102?groupid=364997627165697&refid=18&__tn__=R", "Cmt": "coi tik tok ông này luôn làm khúc cuối nó liền với khúc đầu bánh cuốn vãi :v", "Number reply": 8, "Reply cmt": [{"Owner": "Trần Thái An", "URL Owner": "https://m.facebook.com/ThaiAn0304?groupid=364997627165697&__tn__=R", "Cmt": "Tân Lê đúng rồi á bác, nếu k để ý nó cứ giống như 1 vòng luôn :))", "Number reply": 0}, {"Owner": "Nguyễn Thế Thành Đạt", "URL Owner": "https://m.facebook.com/juunirippou?groupid=364997627165697&__tn__=R", "Cmt": "Họ có bí kíp đấy\nQuay đoạn cuối rồi lộn lên đầu", "Number reply": 0}, {"Owner": "Nga Tuyết Nguyễn", "URL Owner": "https://m.facebook.com/nguyen.t.nga.18?groupid=364997627165697&__tn__=R", "Cmt": "Tân Lê toàn xem đến lần thứ 2, 3 mới thấy ủa? Đoạn này coi rồi mà😅", "Number reply": 0}, {"Owner": "Hồ Toàn", "URL Owner": "https://m.facebook.com/ho.toan.7922hvt?groupid=364997627165697&__tn__=R", "Cmt": "E xin nick tik tok của ông này với", "Number reply": 0}, {"Owner": "Híu Hữu", "URL Owner": "https://m.facebook.com/hieu.ekko282?groupid=364997627165697&__tn__=R", "Cmt": "Tân Lê Giao heo nữa, một vòng lặp luôn", "Number reply": 0}, {"Owner": "Lê Hiệp", "URL Owner": "https://m.facebook.com/Hieple.852?groupid=364997627165697&__tn__=R", "Cmt": "Hồ Toàn tên là Bino chém tiếng anh", "Number reply": 0}, {"Owner": "Lý Minh Hoàng", "URL Owner": "https://m.facebook.com/Krilinz98w?groupid=364997627165697&__tn__=R", "Cmt": "lên top top gõ bino tiếng anh là ra ngay", "Number reply": 0}, {"Owner": "Phạm Quốc Duy", "URL Owner": "https://m.facebook.com/PhamQuocDuy1202?groupid=364997627165697&__tn__=R", "Cmt": "Tân Lê ông Giao Heo làm đồ ăn cũng giống vậy", "Number reply": 0}]}, {"Owner": "Trần Quốc Bảo", "URL Owner": "https://m.facebook.com/profile.php?id=100010789951792&groupid=364997627165697&refid=18&__tn__=R", "Cmt": "\"Pa đờ phai\" là công ty nào thế các bác, em ngu tiếng anh nên nghe mãi k ra :(", "Number reply": 17, "Reply cmt": [{"Owner": "Hồ Duy Thanh", "URL Owner": "https://m.facebook.com/hoduythanh5595?groupid=364997627165697&__tn__=R", "Cmt": "Trần Quốc Bảo sờ pót ti phây", "Number reply": 0}, {"Owner": "Minh Anh Nguyen", "URL Owner": "https://m.facebook.com/minhanh.txm?groupid=364997627165697&__tn__=R", "Cmt": "Trần Quốc Bảo spotify", "Number reply": 0}, {"Owner": "Vũ Ngọc Đức Long", "URL Owner": "https://m.facebook.com/long.vu10101998?groupid=364997627165697&__tn__=R", "Cmt": "Trần Quốc Bảo Spotify thì phải", "Number reply": 0}, {"Owner": "Lê Sơn", "URL Owner": "https://m.facebook.com/profile.php?id=100053768265276&groupid=364997627165697&__tn__=R", "Cmt": "Trần Quốc Bảo Spotify", "Number reply": 0}, {"Owner": "Minh Q. Hoang", "URL Owner": "https://m.facebook.com/minh.q.hoang910?groupid=364997627165697&__tn__=R", "Cmt": "Spotify bro à", "Number reply": 0}, {"Owner": "Hữu Nhânn Nguyễn", "URL Owner": "https://m.facebook.com/140102264100x?groupid=364997627165697&__tn__=R", "Cmt": "Spotify chăng", "Number reply": 0}, {"Owner": "Lê Hữu Võ Long", "URL Owner": "https://m.facebook.com/0x00008123?groupid=364997627165697&__tn__=R", "Cmt": "mình nghe ra \"sờ pa tờ phai\" :v", "Number reply": 0}, {"Owner": "Hoàng Trí Tuệ", "URL Owner": "https://m.facebook.com/bignose.vincent?groupid=364997627165697&__tn__=R", "Cmt": "Spotify mah lord :3", "Number reply": 0}, {"Owner": "Phuc", "URL Owner": "https://m.facebook.com/Chocopie.2911?groupid=364997627165697&__tn__=R", "Cmt": "Trần Quốc Bảo ông này phát âm là thuần tây không kiểu việt cho dễ nghe đâu :v", "Number reply": 0}, {"Owner": "Lương Dân Tiến", "URL Owner": "https://m.facebook.com/luongdantien2?groupid=364997627165697&__tn__=R", "Cmt": "Trần Quốc Bảo Spotify đó bác", "Number reply": 0}, {"Owner": "Luộc Đỗ", "URL Owner": "https://m.facebook.com/luoc.do.03?groupid=364997627165697&__tn__=R", "Cmt": "Trần Quốc Bảo Phát âm kiểu anh mỹ khác anh anh bác ạ", "Number reply": 0}, {"Owner": "Nguyễn Đức Nam Cường", "URL Owner": "https://m.facebook.com/CuongPenguin?groupid=364997627165697&__tn__=R", "Cmt": "Trần Quốc Bảo Spotify đấy bro", "Number reply": 0}, {"Owner": "Trần Hùng", "URL Owner": "https://m.facebook.com/ko.biet.395454?groupid=364997627165697&__tn__=R", "Cmt": "Trần Quốc Bảo Việt nghe quen sờ pót ti phai", "Number reply": 0}, {"Owner": "Duy Lucas", "URL Owner": "https://m.facebook.com/tuitendi2k?groupid=364997627165697&__tn__=R", "Cmt": "Trần Quốc Bảo bác nghe kì thế, e nghe ra spotify ấy", "Number reply": 0}, {"Owner": "Nguyễn Đình Dương", "URL Owner": "https://m.facebook.com/duyang96vn?groupid=364997627165697&__tn__=R", "Cmt": "Phuc sờ pa đờ phai", "Number reply": 0}, {"Owner": "Nguyen Quang Minh", "URL Owner": "https://m.facebook.com/anhbitanhsaioy?groupid=364997627165697&__tn__=R", "Cmt": "Trần Quốc Bảo là spotify đó ông accent mỗi nước khác nhau vn nghe accent mỹ nhiều nên nhiều lúc nghe accent khác ko ra đâu", "Number reply": 0}, {"Owner": "Vương Nghị", "URL Owner": "https://m.facebook.com/p.taycan?groupid=364997627165697&__tn__=R", "Cmt": "Trần Quốc Bảo bác trog vid này nói “Spotify” chuẩn Mĩ đấy", "Number reply": 0}]}, {"Owner": "Hiếu Nghĩa", "URL Owner": "https://m.facebook.com/hnghia62?groupid=364997627165697&refid=18&__tn__=R", "Cmt": "Đấy mới chỉ tính lương, còn thu nhập thì chắc khủng hơn nữa", "Number reply": 1, "Reply cmt": [{"Owner": "Trần Tiến Thành", "URL Owner": "https://m.facebook.com/tung.nit?groupid=364997627165697&__tn__=R", "Cmt": "Hiếu Nghĩa em giàu có khác 🙂 cái gì cũng biết", "Number reply": 0}]}, {"Owner": "Len Hậu", "URL Owner": "https://m.facebook.com/i.am.3000?groupid=364997627165697&refid=18&__tn__=R", "Cmt": "Hôm qua mới nghe chuyện thằng em 97 mua xe, mua 2 con nhà nữa. Nay lại video và 1 đống comment lương mà thấy muốn bỏ việc quá 😢", "Number reply": 0}, {"Owner": "Nguyễn Công Hùng", "URL Owner": "https://m.facebook.com/hung.nguyencong.3114?groupid=364997627165697&refid=18&__tn__=R", "Cmt": "Sn 86 mà làm cho spotify mảng gì để được từng đấy lương với thưởng định kỳ quý trời 🤤", "Number reply": 0}, {"Owner": "Phạm Trường Minh", "URL Owner": "https://m.facebook.com/truongminh55?groupid=364997627165697&refid=18&__tn__=R", "Cmt": "Cao nhất mình từng thấy là gần tỏi, làm tư vấn bảo hiểm tại Manulife.", "Number reply": 2, "Reply cmt": [{"Owner": "Phạm Trường Minh", "URL Owner": "https://m.facebook.com/truongminh55?groupid=364997627165697&__tn__=R", "Cmt": "à, monthly nhé các bác.", "Number reply": 0}, {"Owner": "Nguyễn Hiếu", "URL Owner": "https://m.facebook.com/trunghieuth10?groupid=364997627165697&__tn__=R", "Cmt": "Phạm Trường Minh chuẩn. Hôm em xem đến nửa tháng mà đã hơn 600 củ rồi :))", "Number reply": 0}]}, {"Owner": "Nhật Nhỏ Nhắn", "URL Owner": "https://m.facebook.com/madbee.97?groupid=364997627165697&refid=18&__tn__=R", "Cmt": "Sếp cũ. Năm 80 ổng kiếm 2 3k đô 1 ngày 😂", "Number reply": 0}, {"Owner": "Sơn", "URL Owner": "https://m.facebook.com/waterun.deep?groupid=364997627165697&refid=18&__tn__=R", "Cmt": "anh này có kênh youtube ko các bác", "Number reply": 0}, {"Owner": "Trương Đức Cường", "URL Owner": "https://m.facebook.com/ducuong1987?groupid=364997627165697&refid=18&__tn__=R", "Cmt": "Đó chính là anh ruột tôi, lương tháng 14 triệu. Sinh năm 80. Đến giờ ông ý về hưu và có 3 cái nhà ++!.", "Number reply": 4, "Reply cmt": [{"Owner": "Lê Văn Dũng", "URL Owner": "https://m.facebook.com/le.dung21?groupid=364997627165697&__tn__=R", "Cmt": "Trương Đức Cường 14tr mà có 3 cái nhà luôn à bác", "Number reply": 0}, {"Owner": "Bạn Xoài Giấu Tên", "URL Owner": "https://m.facebook.com/profile.php?id=100009608056002&groupid=364997627165697&__tn__=R", "Cmt": "Trương Đức Cường 80 về hưu sớm hả bác", "Number reply": 0}, {"Owner": "Trương Đức Cường", "URL Owner": "https://m.facebook.com/ducuong1987?groupid=364997627165697&__tn__=R", "Cmt": "Bạn Xoài Giấu Tên Đóng đủ bảo hiểm và bảo hiểm nhân thọ.... Về hưu :v", "Number reply": 0}, {"Owner": "Bạn Xoài Giấu Tên", "URL Owner": "https://m.facebook.com/profile.php?id=100009608056002&groupid=364997627165697&__tn__=R", "Cmt": "Trương Đức Cường giờ này cho thuê 3 căn kia sống thôi chứ chưa được nhận lương hưu bác nhỉ", "Number reply": 0}]}, {"Owner": "Rang Cun", "URL Owner": "https://m.facebook.com/dohuong0202?groupid=364997627165697&refid=18&__tn__=R", "Cmt": "A Đức Lê nhân vật x lương hơn 40tr vào những năm 2004, 2005 😌\nBây giờ ko tính bằng tiền triệu nữa rùi 😔", "Number reply": 0}, {"Owner": "Duy Tran", "URL Owner": "https://m.facebook.com/HiImDuyTran?groupid=364997627165697&refid=18&__tn__=R", "Cmt": "có fl tiktok anh này, video xem khá hay :v", "Number reply": 1, "Reply cmt": [{"Owner": "Tung Ngo", "URL Owner": "https://m.facebook.com/Tung.Ngo.99?groupid=364997627165697&__tn__=R", "Cmt": "Duy Tran Tên acc anh này là gì thế bạn ơi", "Number reply": 0}]}, {"Owner": "Nguyễn Tuấn Thành", "URL Owner": "https://m.facebook.com/hgdhdfhgfhfg1?groupid=364997627165697&refid=18&__tn__=R", "Cmt": "12m các bác ạ", "Number reply": 0}, {"Owner": "Pham Minh Duc", "URL Owner": "https://m.facebook.com/PMjnhDuck?groupid=364997627165697&refid=18&__tn__=R", "Cmt": "Mình chỉ cần lương bằng ổng trừ 1 số 0 là ngon lắm rồi :<", "Number reply": 0}, {"Owner": "Trần Văn Trung", "URL Owner": "https://m.facebook.com/dingiprokg?groupid=364997627165697&refid=18&__tn__=R", "Cmt": "Nhầm gì với mấy anh làm trùm ytb vs momo tháng 4 50 tỷ", "Number reply": 0}, {"Owner": "Khánh Tr", "URL Owner": "https://m.facebook.com/trankhanh.valentine?groupid=364997627165697&refid=18&__tn__=R", "Cmt": "Ông này nói giọng hấp dẫn thật. Xem video ô này cuốn phết.", "Number reply": 0}, {"Owner": "Giang Thư Kỳ", "URL Owner": "https://m.facebook.com/suti11248899?groupid=364997627165697&refid=18&__tn__=R", "Cmt": "Quân Minh Nguyễn lương 1 trẹo 1 tháng tag m cho trầm cảm chung 😞", "Number reply": 0}, {"Owner": "Thành Đức", "URL Owner": "https://m.facebook.com/profile.php?id=100015119656865&groupid=364997627165697&__tn__=R", "Cmt": "245tr500k/tháng của một chị khách nhờ in hợp đồng lao động , giám đốc nhân sự", "Number reply": 0}, {"Owner": "Lê Vũ", "URL Owner": "https://m.facebook.com/levu103?groupid=364997627165697&__tn__=R", "Cmt": "Follow bạn này ở đâu vậy mấy thím? Phát âm tiếng anh hay quá", "Number reply": 3, "Reply cmt": [{"Owner": "Huy Không", "URL Owner": "https://m.facebook.com/huykhoong?groupid=364997627165697&__tn__=R", "Cmt": "Lê Vũ tiktok b\"bino nói tiếng Anh\"", "Number reply": 0}, {"Owner": "Hoang Anh", "URL Owner": "https://m.facebook.com/moriaty.jim.3?groupid=364997627165697&__tn__=R", "Cmt": "Lê Vũ tiktok thẳng tiến", "Number reply": 0}, {"Owner": "Lê Vũ", "URL Owner": "https://m.facebook.com/levu103?groupid=364997627165697&__tn__=R", "Cmt": "Huy Không thanks thím nhé", "Number reply": 0}]}, {"Owner": "Duy Lăng", "URL Owner": "https://m.facebook.com/DuyLang.2000?groupid=364997627165697&__tn__=R", "Cmt": "lương Vozer cũng 350tr/ tháng, kém gì đâu ạ🐧", "Number reply": 0}, {"Owner": "Mẫn Duy", "URL Owner": "https://m.facebook.com/taduyman196?groupid=364997627165697&__tn__=R", "Cmt": "Xoàng, mình làm 25 ngàn 1 giờ nè", "Number reply": 0}, {"Owner": "Trịnh Đức", "URL Owner": "https://m.facebook.com/DucTv22?groupid=364997627165697&__tn__=R", "Cmt": "Của em,vào cuối năm 2021 :v", "Number reply": 8, "Reply cmt": [{"Owner": "Nguyễn Huỳnh Duy Tân", "URL Owner": "https://m.facebook.com/duytan.nguyenhuynh.3?groupid=364997627165697&__tn__=R", "Cmt": "Trịnh Đức Ôi người anh em xa xứ :)))))", "Number reply": 0}, {"Owner": "Trịnh Đức", "URL Owner": "https://m.facebook.com/DucTv22?groupid=364997627165697&__tn__=R", "Cmt": "Nguyễn Huỳnh Duy Tân đấy,chỉ thế là nhanh =))\nQuay về quản lý gr cùng tôi ngay", "Number reply": 0}, {"Owner": "Nguyễn Huỳnh Duy Tân", "URL Owner": "https://m.facebook.com/duytan.nguyenhuynh.3?groupid=364997627165697&__tn__=R", "Cmt": "Trịnh Đức :))))))) để drop bên dịch ln đã", "Number reply": 0}, {"Owner": "Trịnh Đức", "URL Owner": "https://m.facebook.com/DucTv22?groupid=364997627165697&__tn__=R", "Cmt": "Nguyễn Huỳnh Duy Tân tham vãi,về với tôi,50k/ tháng =))", "Number reply": 0}, {"Owner": "Nguyễn Huỳnh Duy Tân", "URL Owner": "https://m.facebook.com/duytan.nguyenhuynh.3?groupid=364997627165697&__tn__=R", "Cmt": "Trịnh Đức Tăng thêm con 0 là năng suất ngay :))))", "Number reply": 0}, {"Owner": "Trịnh Đức", "URL Owner": "https://m.facebook.com/DucTv22?groupid=364997627165697&__tn__=R", "Cmt": "Nguyễn Huỳnh Duy Tân", "Number reply": 0}, {"Owner": "Nguyễn Huỳnh Duy Tân", "URL Owner": "https://m.facebook.com/duytan.nguyenhuynh.3?groupid=364997627165697&__tn__=R", "Cmt": "Trịnh Đức Nốt 3 4 tuần nữa về làm lại :)))) hứa", "Number reply": 0}, {"Owner": "Trịnh Đức", "URL Owner": "https://m.facebook.com/DucTv22?groupid=364997627165697&__tn__=R", "Cmt": "Nguyễn Huỳnh Duy Tân nhớ đấy =))", "Number reply": 0}]}, {"Owner": "Nguyễn Anh Đức", "URL Owner": "https://m.facebook.com/danssyvn?groupid=364997627165697&__tn__=R", "Cmt": "biết mấy ông anh làm POD nói tên nghề ra auto được duyệt khỏi cần bảng lương 🥲", "Number reply": 1, "Reply cmt": [{"Owner": "Nguyễn Hải", "URL Owner": "https://m.facebook.com/profile.php?id=100010660362954&groupid=364997627165697&__tn__=R", "Cmt": "Nguyễn Anh Đức POD thì tầm này nhạt thôi", "Number reply": 0}]}, {"Owner": "Ta Phuong Lam", "URL Owner": "https://m.facebook.com/ikeisictin?groupid=364997627165697&__tn__=R", "Cmt": "Chị của bạn mình bán kem trộn tháng lãi 2-300tr 👁️👄👁️", "Number reply": 1, "Reply cmt": [{"Owner": "Hiếu Nghĩa", "URL Owner": "https://m.facebook.com/hnghia62?groupid=364997627165697&__tn__=R", "Cmt": "Ta Phuong Lam Đây là thu nhập chứ không phải lương bác", "Number reply": 0}]}, {"Owner": "Phạm Trọng Huy", "URL Owner": "https://m.facebook.com/phamtronghuy242?groupid=364997627165697&__tn__=R", "Cmt": "e còn đg định đi xin hộ nghèo\nae nào đi chung không :))", "Number reply": 0}, {"Owner": "Bó Tay", "URL Owner": "https://m.facebook.com/Bettyinfact?groupid=364997627165697&__tn__=R", "Cmt": "má ơi cái đoạn cuối video cắt như đấm vào mặt tôi....\"còn các bạn thì\"\ncòn tôi thì cái nịt anh ạ 😭", "Number reply": 1, "Reply cmt": [{"Owner": "Hoà La", "URL Owner": "https://m.facebook.com/hoa.lavan.90?groupid=364997627165697&__tn__=R", "Cmt": "Bó Tay bạn ghép với câu đầu là thấy magic liền, này là video loop đó =))", "Number reply": 0}]}, {"Owner": "Trinh Truong Thanh", "URL Owner": "https://m.facebook.com/tiron7140?groupid=364997627165697&__tn__=R", "Cmt": "400tr, ớn ăn thiệt", "Number reply": 0}, {"Owner": "Anthony Anh Nguyen", "URL Owner": "https://m.facebook.com/anthony.nguyenvu?groupid=364997627165697&__tn__=R", "Cmt": "Mình lên Voz thấy AE nói ngàn tỉ trăm tỉ kiểu như cái tăm, mớ rau 🤑🤑🤑", "Number reply": 0}, {"Owner": "Minh Anh Nguyen", "URL Owner": "https://m.facebook.com/minhanh.txm?groupid=364997627165697&__tn__=R", "Cmt": "Video hay phết", "Number reply": 0}, {"Owner": "Hưng Nè", "URL Owner": "https://m.facebook.com/tanhung43?groupid=364997627165697&__tn__=R", "Cmt": "như ông anh mình nè, đang từ cơ khí qua bách khoa... :v\nVân Nhi", "Number reply": 1, "Reply cmt": [{"Owner": "Vân Nhi", "URL Owner": "https://m.facebook.com/profile.php?id=100007107369889&groupid=364997627165697&__tn__=R", "Cmt": "Hưng Nè văn mẫu à😌", "Number reply": 0}]}, {"Owner": "Nam Nguyễn", "URL Owner": "https://m.facebook.com/nambg984?groupid=364997627165697&__tn__=R", "Cmt": "Anh Bino đang nói là 21k đô Úc, còn đô la mẽo thì không biết 😂", "Number reply": 2, "Reply cmt": [{"Owner": "Khang Võ", "URL Owner": "https://m.facebook.com/khangdz2109?groupid=364997627165697&__tn__=R", "Cmt": "Nam Nguyễn đô Úc đổi ra VNĐ nhiều hơn đô Mỹ fk ông?", "Number reply": 0}, {"Owner": "Nam Nguyễn", "URL Owner": "https://m.facebook.com/nambg984?groupid=364997627165697&__tn__=R", "Cmt": "Khang Duy Võ không ông. Đô úc tầm hơn 16k, đô mẽo thì tầm 23k", "Number reply": 0}]}, {"Owner": "Hoàng Thịnh", "URL Owner": "https://m.facebook.com/dht1909?groupid=364997627165697&__tn__=R", "Cmt": "Trần Lê Duy mạnh dạn tag đại gia vào", "Number reply": 1, "Reply cmt": [{"Owner": "Trần Lê Duy", "URL Owner": "https://m.facebook.com/leduycs?groupid=364997627165697&__tn__=R", "Cmt": "Hoàng Thịnh lương nhà ng ta chứ lương t ko đủ ăn", "Number reply": 0}]}, {"Owner": "Ngọc Lâm", "URL Owner": "https://m.facebook.com/ngoclam.online?groupid=364997627165697&__tn__=R", "Cmt": "Thế thì chưa gặp anh zai Thái Bùi rồi. Anh mình lương tháng 2tr đô nhé.", "Number reply": 1, "Reply cmt": [{"Owner": "Thái Bùi", "URL Owner": "https://m.facebook.com/buithai.31.07.1984?groupid=364997627165697&__tn__=R", "Cmt": "Ngọc Lâm ui em lại chêu anh :((((", "Number reply": 0}]}, {"Owner": "Gia Bảo", "URL Owner": "https://m.facebook.com/profile.php?id=100007639488490&groupid=364997627165697&__tn__=R", "Cmt": "Lương tầm 20k chỗ tôi nhiều", "Number reply": 0}, {"Owner": "Vương Hoàng Ngâm", "URL Owner": "https://m.facebook.com/vuong.ngam?groupid=364997627165697&__tn__=R", "Cmt": "tôi =)) 4tr7", "Number reply": 0}, {"Owner": "Thanh Tâm", "URL Owner": "https://m.facebook.com/thanh.tam881?groupid=364997627165697&__tn__=R", "Cmt": "Khoảng 100 triệu :)))", "Number reply": 0}, null, null, null, null, null, null, null, null, null, null, null, null, null, null, null, null, null, null, null, null, null, null, null, null, null, null, null, null, null, null, null, null, null, null, null, null, null, null]}